vajra_bm25/__init__.py
vajra_bm25/cli.py
vajra_bm25/documents.py
vajra_bm25/inverted_index.py
vajra_bm25/logging_config.py
vajra_bm25/optimized.py
vajra_bm25/parallel.py
vajra_bm25/scorer.py
vajra_bm25/search.py
vajra_bm25/text_processing.py
vajra_bm25/categorical/__init__.py
vajra_bm25/categorical/category.py
vajra_bm25/categorical/coalgebra.py
vajra_bm25/categorical/functor.py
vajra_bm25/vector/__init__.py
vajra_bm25/vector/embeddings.py
vajra_bm25/vector/hybrid.py
vajra_bm25/vector/index.py
vajra_bm25/vector/index_flat.py
vajra_bm25/vector/scorer.py
vajra_bm25/vector/search.py
vajra_bm25/vector/hnsw/__init__.py
vajra_bm25/vector/hnsw/coalgebra.py
vajra_bm25/vector/hnsw/graph.py
vajra_bm25/vector/hnsw/index.py
vajra_bm25/vector/hnsw/state.py
vajra_bm25-0.4.1.dist-info/licenses/LICENSE
vajra_bm25-0.4.1.dist-info/METADATA
vajra_bm25-0.4.1.dist-info/WHEEL
vajra_bm25-0.4.1.dist-info/entry_points.txt
vajra_bm25-0.4.1.dist-info/top_level.txt
vajra_bm25-0.4.1.dist-info/RECORD
