Metadata-Version: 2.4
Name: vajra-bm25
Version: 0.4.1
Summary: Categorical BM25 search engine using pure category theory
Author: Rajesh Sampathkumar
License: MIT
Project-URL: Homepage, https://github.com/aiexplorations/vajra_bm25
Project-URL: Documentation, https://github.com/aiexplorations/vajra_bm25#readme
Project-URL: Repository, https://github.com/aiexplorations/vajra_bm25
Project-URL: Issues, https://github.com/aiexplorations/vajra_bm25/issues
Keywords: bm25,search,category-theory,information-retrieval,coalgebra,morphism,functor,text-search,ranking,vector-search,hnsw,embeddings,hybrid-search
Classifier: Development Status :: 4 - Beta
Classifier: Intended Audience :: Developers
Classifier: Intended Audience :: Science/Research
Classifier: License :: OSI Approved :: MIT License
Classifier: Programming Language :: Python :: 3
Classifier: Programming Language :: Python :: 3.8
Classifier: Programming Language :: Python :: 3.9
Classifier: Programming Language :: Python :: 3.10
Classifier: Programming Language :: Python :: 3.11
Classifier: Programming Language :: Python :: 3.12
Classifier: Topic :: Scientific/Engineering :: Information Analysis
Classifier: Topic :: Text Processing :: Indexing
Classifier: Topic :: Software Development :: Libraries :: Python Modules
Requires-Python: >=3.8
License-File: LICENSE
Provides-Extra: optimized
Requires-Dist: numpy>=1.20.0; extra == "optimized"
Requires-Dist: scipy>=1.7.0; extra == "optimized"
Provides-Extra: persistence
Requires-Dist: joblib>=1.0.0; extra == "persistence"
Provides-Extra: pdf
Requires-Dist: pypdf>=4.0.0; extra == "pdf"
Provides-Extra: vector
Requires-Dist: numpy>=1.20.0; extra == "vector"
Requires-Dist: sentence-transformers>=2.2.0; extra == "vector"
Provides-Extra: vector-numba
Requires-Dist: numpy>=1.20.0; extra == "vector-numba"
Requires-Dist: sentence-transformers>=2.2.0; extra == "vector-numba"
Requires-Dist: numba>=0.56.0; extra == "vector-numba"
Provides-Extra: dev
Requires-Dist: pytest>=7.0; extra == "dev"
Requires-Dist: pytest-cov>=4.0; extra == "dev"
Requires-Dist: rank-bm25>=0.2.2; extra == "dev"
Requires-Dist: pypdf>=4.0.0; extra == "dev"
Provides-Extra: benchmark
Requires-Dist: rank-bm25>=0.2.2; extra == "benchmark"
Requires-Dist: bm25s>=0.1.0; extra == "benchmark"
Requires-Dist: beir>=1.0.0; extra == "benchmark"
Requires-Dist: rich>=13.0.0; extra == "benchmark"
Requires-Dist: tantivy>=0.20.0; extra == "benchmark"
Provides-Extra: benchmark-full
Requires-Dist: rank-bm25>=0.2.2; extra == "benchmark-full"
Requires-Dist: bm25s>=0.1.0; extra == "benchmark-full"
Requires-Dist: beir>=1.0.0; extra == "benchmark-full"
Requires-Dist: rich>=13.0.0; extra == "benchmark-full"
Requires-Dist: tantivy>=0.20.0; extra == "benchmark-full"
Requires-Dist: pyserini>=0.20.0; extra == "benchmark-full"
Provides-Extra: cli
Requires-Dist: rich>=13.0.0; extra == "cli"
Requires-Dist: beir>=1.0.0; extra == "cli"
Provides-Extra: all
Requires-Dist: numpy>=1.20.0; extra == "all"
Requires-Dist: scipy>=1.7.0; extra == "all"
Requires-Dist: joblib>=1.0.0; extra == "all"
Requires-Dist: pypdf>=4.0.0; extra == "all"
Requires-Dist: sentence-transformers>=2.2.0; extra == "all"
Dynamic: license-file
